soda/data_sources/sqlserver_data_source.py
soda_core_sqlserver_samdebruyn-3.5.4.post1.dist-info/METADATA
soda_core_sqlserver_samdebruyn-3.5.4.post1.dist-info/WHEEL
soda_core_sqlserver_samdebruyn-3.5.4.post1.dist-info/top_level.txt
soda_core_sqlserver_samdebruyn-3.5.4.post1.dist-info/RECORD
